{"kind":"FileIndex","apiVersion":"v1","Files":{".classpath":{"Size":1345,"LastModifiedDate":"2020-06-29T13:26:14.3863473+05:30"},".gitignore":{"Size":25,"LastModifiedDate":"2020-06-29T13:38:24.0689291+05:30"},".project":{"Size":1800,"LastModifiedDate":"2020-06-10T10:59:02.2542958+05:30"},".settings":{"Size":4096,"LastModifiedDate":"2020-06-10T10:58:13.6362225+05:30"},".settings/org.eclipse.core.resources.prefs":{"Size":155,"LastModifiedDate":"2020-06-10T10:57:50.0809721+05:30"},".settings/org.eclipse.jdt.core.prefs":{"Size":617,"LastModifiedDate":"2020-06-29T13:26:14.0250916+05:30"},".settings/org.eclipse.m2e.core.prefs":{"Size":90,"LastModifiedDate":"2020-06-10T10:54:51.9841747+05:30"},".settings/org.eclipse.wst.common.component":{"Size":333,"LastModifiedDate":"2020-06-10T10:58:13.49212+05:30"},".settings/org.eclipse.wst.common.project.facet.core.xml":{"Size":267,"LastModifiedDate":"2020-06-29T13:26:14.3067913+05:30"},".settings/org.eclipse.wst.validation.prefs":{"Size":50,"LastModifiedDate":"2020-06-10T10:58:13.521641+05:30"},".settings/org.hibernate.eclipse.console.prefs":{"Size":101,"LastModifiedDate":"2020-06-10T10:58:13.6362225+05:30"},"LICENSE.md":{"Size":11560,"LastModifiedDate":"2020-06-10T10:54:51.9181273+05:30"},"README.md":{"Size":2846,"LastModifiedDate":"2020-06-10T10:54:51.9221305+05:30"},"configuration":{"Size":0,"LastModifiedDate":"2020-06-10T10:54:51.9316377+05:30"},"configuration/settings.xml":{"Size":3806,"LastModifiedDate":"2020-06-10T10:54:51.9321376+05:30"},"pom.xml":{"Size":7795,"LastModifiedDate":"2020-06-29T13:26:04.0301567+05:30"},"src":{"Size":0,"LastModifiedDate":"2020-06-10T10:54:51.9091221+05:30"},"src/data":{"Size":0,"LastModifiedDate":"2020-06-10T10:54:51.9091221+05:30"},"src/main":{"Size":0,"LastModifiedDate":"2020-06-10T10:54:51.9026167+05:30"},"src/main/fabric8":{"Size":0,"LastModifiedDate":"2020-06-10T10:54:51.9036174+05:30"},"src/main/fabric8/deployment.yml":{"Size":382,"LastModifiedDate":"2020-06-10T11:44:29.5334529+05:30"},"src/main/java":{"Size":0,"LastModifiedDate":"2020-06-10T10:58:13.1058466+05:30"},"src/main/java/META-INF":{"Size":0,"LastModifiedDate":"2020-06-10T10:58:13.1068461+05:30"},"src/main/java/META-INF/MANIFEST.MF":{"Size":39,"LastModifiedDate":"2020-06-10T10:58:13.1068461+05:30"},"src/main/java/com":{"Size":0,"LastModifiedDate":"2020-06-10T10:54:51.8841039+05:30"},"src/main/java/com/redhat":{"Size":0,"LastModifiedDate":"2020-06-10T10:54:51.8841039+05:30"},"src/main/java/com/redhat/gpe":{"Size":0,"LastModifiedDate":"2020-06-10T10:54:51.8841039+05:30"},"src/main/java/com/redhat/gpe/training":{"Size":0,"LastModifiedDate":"2020-06-10T10:54:51.8846038+05:30"},"src/main/java/com/redhat/gpe/training/fis":{"Size":0,"LastModifiedDate":"2020-06-10T10:54:51.8886067+05:30"},"src/main/java/com/redhat/gpe/training/fis/Application.java":{"Size":1253,"LastModifiedDate":"2020-06-10T10:54:51.8871056+05:30"},"src/main/java/com/redhat/gpe/training/fis/MyTransformer.java":{"Size":1226,"LastModifiedDate":"2020-06-10T10:54:51.8891075+05:30"},"src/main/resources":{"Size":0,"LastModifiedDate":"2020-06-10T10:54:51.9016159+05:30"},"src/main/resources/application.properties":{"Size":578,"LastModifiedDate":"2020-06-10T10:54:51.8941106+05:30"},"src/main/resources/logback.xml":{"Size":485,"LastModifiedDate":"2020-06-10T10:54:51.9021163+05:30"},"src/main/resources/spring":{"Size":0,"LastModifiedDate":"2020-06-10T10:54:51.9001162+05:30"},"src/main/resources/spring/camel-context.xml":{"Size":982,"LastModifiedDate":"2020-07-01T18:07:44.5818324+05:30"},"src/test":{"Size":0,"LastModifiedDate":"2020-06-10T10:54:51.9061191+05:30"},"src/test/java":{"Size":0,"LastModifiedDate":"2020-06-10T10:54:51.9066191+05:30"},"src/test/java/com":{"Size":0,"LastModifiedDate":"2020-06-10T10:54:51.9066191+05:30"},"src/test/java/com/redhat":{"Size":0,"LastModifiedDate":"2020-06-10T10:54:51.9066191+05:30"},"src/test/java/com/redhat/gpe":{"Size":0,"LastModifiedDate":"2020-06-10T10:54:51.9071199+05:30"},"src/test/java/com/redhat/gpe/training":{"Size":0,"LastModifiedDate":"2020-06-10T10:54:51.9071199+05:30"},"src/test/java/com/redhat/gpe/training/fis":{"Size":0,"LastModifiedDate":"2020-06-10T10:54:51.9071199+05:30"},"target":{"Size":4096,"LastModifiedDate":"2020-07-01T16:38:09.1042208+05:30"},"target/classes":{"Size":0,"LastModifiedDate":"2020-07-01T16:38:09.3423894+05:30"},"target/classes/META-INF":{"Size":0,"LastModifiedDate":"2020-07-01T16:38:09.3759132+05:30"},"target/classes/META-INF/MANIFEST.MF":{"Size":103,"LastModifiedDate":"2020-07-01T16:38:09.3508954+05:30"},"target/classes/META-INF/maven":{"Size":0,"LastModifiedDate":"2020-07-01T16:38:09.3994299+05:30"},"target/classes/META-INF/maven/com.redhat.gpe.training":{"Size":0,"LastModifiedDate":"2020-07-01T16:38:09.4014305+05:30"},"target/classes/META-INF/maven/com.redhat.gpe.training/fis7-camel-springboot":{"Size":0,"LastModifiedDate":"2020-07-01T16:38:09.4244476+05:30"},"target/classes/META-INF/maven/com.redhat.gpe.training/fis7-camel-springboot/pom.properties":{"Size":278,"LastModifiedDate":"2020-07-01T16:38:09.4029319+05:30"},"target/classes/META-INF/maven/com.redhat.gpe.training/fis7-camel-springboot/pom.xml":{"Size":7795,"LastModifiedDate":"2020-07-01T16:38:09.4249471+05:30"},"target/classes/application.properties":{"Size":578,"LastModifiedDate":"2020-07-01T16:37:31.9056683+05:30"},"target/classes/com":{"Size":0,"LastModifiedDate":"2020-07-01T16:37:36.7104887+05:30"},"target/classes/com/redhat":{"Size":0,"LastModifiedDate":"2020-07-01T16:37:36.7104887+05:30"},"target/classes/com/redhat/gpe":{"Size":0,"LastModifiedDate":"2020-07-01T16:37:36.7104887+05:30"},"target/classes/com/redhat/gpe/training":{"Size":0,"LastModifiedDate":"2020-07-01T16:37:36.7275004+05:30"},"target/classes/com/redhat/gpe/training/fis":{"Size":0,"LastModifiedDate":"2020-07-01T16:37:36.7525186+05:30"},"target/classes/com/redhat/gpe/training/fis/Application.class":{"Size":829,"LastModifiedDate":"2020-07-01T16:37:36.7540235+05:30"},"target/classes/com/redhat/gpe/training/fis/MyTransformer.class":{"Size":936,"LastModifiedDate":"2020-07-01T16:37:36.7410112+05:30"},"target/classes/logback.xml":{"Size":485,"LastModifiedDate":"2020-07-01T16:37:31.9076667+05:30"},"target/classes/spring":{"Size":0,"LastModifiedDate":"2020-07-01T16:37:31.9086687+05:30"},"target/classes/spring/camel-context.xml":{"Size":982,"LastModifiedDate":"2020-07-01T18:07:44.9445895+05:30"},"target/generated-sources":{"Size":0,"LastModifiedDate":"2020-07-01T16:37:35.1919104+05:30"},"target/generated-sources/annotations":{"Size":0,"LastModifiedDate":"2020-07-01T16:37:35.1919104+05:30"},"target/maven-status":{"Size":0,"LastModifiedDate":"2020-07-01T16:37:35.1543837+05:30"},"target/maven-status/maven-compiler-plugin":{"Size":0,"LastModifiedDate":"2020-07-01T16:37:36.8761238+05:30"},"target/maven-status/maven-compiler-plugin/compile":{"Size":0,"LastModifiedDate":"2020-07-01T16:37:35.1543837+05:30"},"target/maven-status/maven-compiler-plugin/compile/default-compile":{"Size":0,"LastModifiedDate":"2020-07-01T16:37:36.8395808+05:30"},"target/maven-status/maven-compiler-plugin/compile/default-compile/createdFiles.lst":{"Size":94,"LastModifiedDate":"2020-07-01T16:37:36.8060583+05:30"},"target/maven-status/maven-compiler-plugin/compile/default-compile/inputFiles.lst":{"Size":212,"LastModifiedDate":"2020-07-01T16:37:36.8400807+05:30"},"target/maven-status/maven-compiler-plugin/testCompile":{"Size":0,"LastModifiedDate":"2020-07-01T16:37:36.8761238+05:30"},"target/maven-status/maven-compiler-plugin/testCompile/default-testCompile":{"Size":0,"LastModifiedDate":"2020-07-01T16:37:36.9052004+05:30"},"target/maven-status/maven-compiler-plugin/testCompile/default-testCompile/inputFiles.lst":{"Size":0,"LastModifiedDate":"2020-07-01T16:37:36.9052004+05:30"},"target/test-classes":{"Size":0,"LastModifiedDate":"2020-07-01T16:38:09.1042208+05:30"}}}